melon_translate_client/__init__.py
melon_translate_client/models.py
melon_translate_client/module.py
melon_translate_client/request.py
melon_translate_client/settings.py
melon_translate_client/tests/__init__.py
melon_translate_client/tests/pytest_fixtures.py
melon_translate_client-0.17.1.dist-info/METADATA
melon_translate_client-0.17.1.dist-info/WHEEL
melon_translate_client-0.17.1.dist-info/RECORD
