Metadata-Version: 2.1
Name: melon_translate_client
Version: 0.17.1
Summary: Client package for melon-translate.
Requires-Python: >=3.8,<4.0
Classifier: Programming Language :: Python :: 3
Classifier: Programming Language :: Python :: 3.8
Classifier: Programming Language :: Python :: 3.9
Classifier: Programming Language :: Python :: 3.10
Classifier: Programming Language :: Python :: 3.11
Classifier: Programming Language :: Python :: 3.12
Requires-Dist: gevent
Requires-Dist: python-decouple (>=3.8,<4.0)
Requires-Dist: python-redis-lock (>=4.0.0,<5.0.0)
Requires-Dist: redis (>=5.0.8,<6.0.0)
Requires-Dist: redis-om (>=0.3.1,<0.4.0)
Requires-Dist: requests (>=2.32.3,<3.0.0)
